cnxeasybake/__init__.py
cnxeasybake/_version.py
cnxeasybake/oven.py
cnxeasybake/scripts/__init__.py
cnxeasybake/scripts/main.py
cnxeasybake/tests/__init__.py
cnxeasybake/tests/test_cli.py
cnxeasybake/tests/test_oven.py
cnxeasybake/tests/test_rulesets.py
cnx_easybake-1.2.8.dist-info/LICENSE.txt
cnx_easybake-1.2.8.dist-info/METADATA
cnx_easybake-1.2.8.dist-info/WHEEL
cnx_easybake-1.2.8.dist-info/entry_points.txt
cnx_easybake-1.2.8.dist-info/top_level.txt
cnx_easybake-1.2.8.dist-info/RECORD
