Metadata-Version: 2.1
Name: cnx-easybake
Version: 1.2.8
Summary: UNKNOWN
Home-page: https://github.com/connexions/cnx-easybake
Author: Connexions team
Author-email: info@cnx.org
License: LGPL, See also LICENSE.txt
Platform: UNKNOWN
Requires-Dist: cssselect
Requires-Dist: cnx-cssselect2
Requires-Dist: tinycss2 (<1.0.0)
Requires-Dist: lxml (==4.4.3)
Requires-Dist: PyICU
Requires-Dist: PyICU (==1.9.8) ; platform_system == "Darwin"
